setup.py
flashops/__init__.py
flashops/__main__.py
flashops/main.py
flashops/syncutils.py
flashops.egg-info/PKG-INFO
flashops.egg-info/SOURCES.txt
flashops.egg-info/dependency_links.txt
flashops.egg-info/entry_points.txt
flashops.egg-info/requires.txt
flashops.egg-info/top_level.txt