Metadata-Version: 2.1
Name: flashops
Version: 19.1.6
Summary: Simplify Linux Server Operations and Maintenance
Home-page: https://github.com/dongyg
Author: dongyg
Author-email: mikedong927@gmail.com
License: MIT
Platform: UNKNOWN
Classifier: Intended Audience :: Developers
Classifier: License :: OSI Approved :: MIT License
Classifier: Programming Language :: Python :: 2.7
Classifier: Programming Language :: Python :: 3.4
Classifier: Programming Language :: Python :: 3.5
Classifier: Programming Language :: Python :: 3.6
